emploo/__init__.py
emploo/__main__.py
emploo-0.1.2.dist-info/METADATA
emploo-0.1.2.dist-info/WHEEL
emploo-0.1.2.dist-info/entry_points.txt
emploo-0.1.2.dist-info/licenses/LICENSE
emploo-0.1.2.dist-info/RECORD
