Metadata-Version: 2.1
Name: emploo
Version: 0.1.2
Summary: A command-line tool to lookup employees for a given company.
Project-URL: Homepage, https://github.com/4383/emploo
Project-URL: History, https://github.com/4383/emploo/blob/main/CHANGELOG.md
Project-URL: Sponsor, https://github.com/sponsors/4383
Project-URL: Tracker, https://github.com/4383/emploo/issues
Project-URL: Source, https://github.com/4383/emploo
Author-email: Hervé Beraud <herveberaud.pro@gmail.com>
License: MIT
License-File: LICENSE
Classifier: Development Status :: 3 - Alpha
Classifier: Environment :: Console
Classifier: Intended Audience :: Developers
Classifier: License :: OSI Approved :: MIT License
Classifier: Operating System :: OS Independent
Classifier: Programming Language :: Python
Classifier: Programming Language :: Python :: 3
Classifier: Programming Language :: Python :: 3.9
Classifier: Programming Language :: Python :: 3.10
Classifier: Programming Language :: Python :: 3.11
Classifier: Programming Language :: Python :: 3.12
Classifier: Topic :: Security
Classifier: Topic :: Sociology
Classifier: Topic :: Software Development
Requires-Python: >=3.9
Requires-Dist: requests
Provides-Extra: dev
Requires-Dist: black; extra == 'dev'
Requires-Dist: build; extra == 'dev'
Requires-Dist: commitizen; extra == 'dev'
Requires-Dist: isort; extra == 'dev'
Requires-Dist: pip-tools; extra == 'dev'
Requires-Dist: pre-commit; extra == 'dev'
Requires-Dist: twine; extra == 'dev'
